[{"branch_id": 1104, "relationship_manager_id": 588696, "first_name": "ldvfrvnucun", "last_name": "MVRLPCRNJAPJ", "last_updated": "2012-12-28"}, {"branch_id": 1654, "relationship_manager_id": 597080, "first_name": "hlhdhyvdw", "last_name": "NOZQLILC", "last_updated": "2005-08-29"}, {"branch_id": 1250, "relationship_manager_id": 571482, "first_name": "qrydj", "last_name": "UBMHTPYVZ", "last_updated": "2007-05-19"}, {"branch_id": 1250, "relationship_manager_id": 511395, "first_name": "q", "last_name": "J", "last_updated": "2003-01-14"}, {"branch_id": 1654, "relationship_manager_id": 577397, "first_name": "e", "last_name": "NDPLWKSTIHDVQ", "last_updated": "2017-06-08"}, {"branch_id": 1142, "relationship_manager_id": 555302, "first_name": "g", "last_name": "M", "last_updated": "2002-10-28"}, {"branch_id": 1228, "relationship_manager_id": 504165, "first_name": "bzz", "last_name": "IFCPDNMLBJUNECR", "last_updated": "2011-05-07"}, {"branch_id": 1228, "relationship_manager_id": 503905, "first_name": "lxizdbt", "last_name": "I", "last_updated": "2019-12-22"}, {"branch_id": 1759, "relationship_manager_id": 512280, "first_name": "bn", "last_name": "KOCCOANBENEE", "last_updated": "2019-08-03"}, {"branch_id": 1754, "relationship_manager_id": 528657, "first_name": "qdrgrzuiix", "last_name": "EIWGHFNOKP", "last_updated": "2019-10-13"}, {"branch_id": 1654, "relationship_manager_id": 530495, "first_name": "ivaqnc", "last_name": "JWMUEYRMADWRAX", "last_updated": "2002-05-02"}, {"branch_id": 1654, "relationship_manager_id": 566237, "first_name": "td", "last_name": "PGLA", "last_updated": "2014-12-07"}, {"branch_id": 1281, "relationship_manager_id": 578907, "first_name": "swsyyycuvvwj", "last_name": "QOBHYGQG", "last_updated": "2015-12-14"}, {"branch_id": 1228, "relationship_manager_id": 503478, "first_name": "", "last_name": "QMVWRJGGPQNJJKG", "last_updated": "2011-02-16"}, {"branch_id": 1228, "relationship_manager_id": 573563, "first_name": "oilrfald", "last_name": "BKNTVYT", "last_updated": "2000-10-07"}, {"branch_id": 1754, "relationship_manager_id": 526062, "first_name": "koufmrugeh", "last_name": "QKKNGVFMSWTEZ", "last_updated": "2007-01-02"}, {"branch_id": 1759, "relationship_manager_id": 593850, "first_name": "sscygtdrlyr", "last_name": "NKNUVFPABKK", "last_updated": "2012-07-04"}, {"branch_id": 1142, "relationship_manager_id": 585181, "first_name": "fcaoxblwekyjnjy", "last_name": "OPOGIJUIOSWZ", "last_updated": "2012-04-01"}, {"branch_id": 1281, "relationship_manager_id": 591924, "first_name": "dym", "last_name": "VXBU", "last_updated": "2019-03-26"}, {"branch_id": 1025, "relationship_manager_id": 571426, "first_name": "e", "last_name": "LISWWAGRMGH", "last_updated": "2014-11-11"}, {"branch_id": 1654, "relationship_manager_id": 554987, "first_name": "hvjbwt", "last_name": "QGRMGLKI", "last_updated": "2001-06-06"}, {"branch_id": 1281, "relationship_manager_id": 528893, "first_name": "ou", "last_name": "GPBMLX", "last_updated": "2003-04-17"}, {"branch_id": 1281, "relationship_manager_id": 558878, "first_name": "wxpgbpsqto", "last_name": "DKC", "last_updated": "2005-01-03"}, {"branch_id": 1759, "relationship_manager_id": 577236, "first_name": "lajwdnunbraodv", "last_name": "KLEPPC", "last_updated": "2015-11-11"}, {"branch_id": 1025, "relationship_manager_id": 536463, "first_name": "firalb", "last_name": "HYZYOEC", "last_updated": "2005-03-20"}, {"branch_id": 1754, "relationship_manager_id": 500851, "first_name": "oqdmqddbckvoir", "last_name": "NT", "last_updated": "2020-06-23"}, {"branch_id": 1754, "relationship_manager_id": 599458, "first_name": "xgqepcvrfic", "last_name": "RRTLUTNXN", "last_updated": "2011-09-08"}, {"branch_id": 1114, "relationship_manager_id": 520926, "first_name": "cvbjtulldugcp", "last_name": "TIK", "last_updated": "2005-08-15"}, {"branch_id": 1654, "relationship_manager_id": 591506, "first_name": "garpltnaldl", "last_name": "XIBNAS", "last_updated": "2005-04-21"}, {"branch_id": 1250, "relationship_manager_id": 555392, "first_name": "bgcwdrrlwxgj", "last_name": "LPCSMSWYT", "last_updated": "2004-12-21"}, {"branch_id": 1654, "relationship_manager_id": 544597, "first_name": "fmiyneeprln", "last_name": "UH", "last_updated": "2018-08-28"}, {"branch_id": 1114, "relationship_manager_id": 536421, "first_name": "ncgqqxuvx", "last_name": "PIR", "last_updated": "2020-10-07"}, {"branch_id": 1142, "relationship_manager_id": 520379, "first_name": "efxemoq", "last_name": "FSBNHQKPIOAIP", "last_updated": "2002-11-01"}, {"branch_id": 1025, "relationship_manager_id": 528221, "first_name": "jl", "last_name": "KVJAJYGG", "last_updated": "2018-08-15"}, {"branch_id": 1281, "relationship_manager_id": 544118, "first_name": "kzpnxc", "last_name": "WTFVFTHFO", "last_updated": "2008-02-11"}, {"branch_id": 1281, "relationship_manager_id": 513396, "first_name": "kndtjklq", "last_name": "CTCIINWXXRJHR", "last_updated": "2019-01-01"}, {"branch_id": 1759, "relationship_manager_id": 512156, "first_name": "bydqfhgntsepvzl", "last_name": "EQHLXRLMYJHIUHC", "last_updated": "2012-11-10"}, {"branch_id": 1114, "relationship_manager_id": 549797, "first_name": "dq", "last_name": "TRHQQJOTIZZOZ", "last_updated": "2006-01-17"}, {"branch_id": 1142, "relationship_manager_id": 512676, "first_name": "hunpvdpc", "last_name": "NFEANQZFQPMWQX", "last_updated": "2016-03-09"}, {"branch_id": 1228, "relationship_manager_id": 547052, "first_name": "ienj", "last_name": "X", "last_updated": "2015-10-08"}, {"branch_id": 1759, "relationship_manager_id": 545082, "first_name": "wympcnsw", "last_name": "G", "last_updated": "2000-09-21"}, {"branch_id": 1114, "relationship_manager_id": 579131, "first_name": "", "last_name": "IXUVUUSMOI", "last_updated": "2004-10-22"}, {"branch_id": 1654, "relationship_manager_id": 534671, "first_name": "qqqsure", "last_name": "RZORWVLFMWG", "last_updated": "2019-05-23"}, {"branch_id": 1759, "relationship_manager_id": 505695, "first_name": "yxlqbpgepvl", "last_name": "ZNWQZX", "last_updated": "2008-02-09"}, {"branch_id": 1025, "relationship_manager_id": 595647, "first_name": "", "last_name": "UVCUCZM", "last_updated": "2019-02-09"}, {"branch_id": 1281, "relationship_manager_id": 560217, "first_name": "j", "last_name": "JXE", "last_updated": "2019-06-01"}, {"branch_id": 1025, "relationship_manager_id": 570284, "first_name": "a", "last_name": "OYDGSLEBU", "last_updated": "2019-09-20"}, {"branch_id": 1104, "relationship_manager_id": 516361, "first_name": "xvuztvoiotlsmn", "last_name": "PPHFAUDPZUO", "last_updated": "2001-03-28"}, {"branch_id": 1759, "relationship_manager_id": 549615, "first_name": "nxu", "last_name": "LDGZKTQSO", "last_updated": "2017-09-12"}, {"branch_id": 1114, "relationship_manager_id": 510328, "first_name": "mrghehcibr", "last_name": "SKXUFW", "last_updated": "2020-09-21"}]